[
    {
        "time": "0.75",
        "simple_pattern_type": "1",
        "hard_pattern_type": "0",
        "action_num": "0",
        "ready": "FALSE",
        "": ""
    },
    {
        "time": "1.13",
        "simple_pattern_type": "1",
        "hard_pattern_type": "0",
        "action_num": "0",
        "ready": "FALSE",
        "": ""
    },
    {
        "time": "1.315",
        "simple_pattern_type": "1",
        "hard_pattern_type": "0",
        "action_num": "0",
        "ready": "FALSE",
        "": ""
    },
    {
        "time": "1.5",
        "simple_pattern_type": "1",
        "hard_pattern_type": "0",
        "action_num": "0",
        "ready": "FALSE",
        "": ""
    },
    {
        "time": "2.06",
        "simple_pattern_type": "1",
        "hard_pattern_type": "0",
        "action_num": "0",
        "ready": "FALSE",
        "": ""
    },
    {
        "time": "2.25",
        "simple_pattern_type": "1",
        "hard_pattern_type": "0",
        "action_num": "0",
        "ready": "FALSE",
        "": ""
    },
    {
        "time": "3",
        "simple_pattern_type": "1",
        "hard_pattern_type": "0",
        "action_num": "0",
        "ready": "FALSE",
        "": ""
    },
    {
        "time": "3.75",
        "simple_pattern_type": "1",
        "hard_pattern_type": "0",
        "action_num": "0",
        "ready": "FALSE",
        "": ""
    },
    {
        "time": "4.12",
        "simple_pattern_type": "1",
        "hard_pattern_type": "0",
        "action_num": "0",
        "ready": "FALSE",
        "": ""
    },
    {
        "time": "4.31",
        "simple_pattern_type": "1",
        "hard_pattern_type": "0",
        "action_num": "0",
        "ready": "FALSE",
        "": ""
    },
    {
        "time": "4.5",
        "simple_pattern_type": "1",
        "hard_pattern_type": "0",
        "action_num": "0",
        "ready": "FALSE",
        "": ""
    },
    {
        "time": "5.06",
        "simple_pattern_type": "1",
        "hard_pattern_type": "0",
        "action_num": "0",
        "ready": "FALSE",
        "": ""
    },
    {
        "time": "5.25",
        "simple_pattern_type": "2",
        "hard_pattern_type": "0",
        "action_num": "0",
        "ready": "TRUE",
        "": ""
    },
    {
        "time": "6",
        "simple_pattern_type": "2",
        "hard_pattern_type": "0",
        "action_num": "1",
        "ready": "FALSE",
        "": ""
    },
    {
        "time": "6.75",
        "simple_pattern_type": "2",
        "hard_pattern_type": "0",
        "action_num": "1",
        "ready": "FALSE",
        "": ""
    },
    {
        "time": "7.125",
        "simple_pattern_type": "2",
        "hard_pattern_type": "0",
        "action_num": "1",
        "ready": "FALSE",
        "": ""
    },
    {
        "time": "7.31",
        "simple_pattern_type": "2",
        "hard_pattern_type": "0",
        "action_num": "1",
        "ready": "FALSE",
        "": ""
    },
    {
        "time": "7.5",
        "simple_pattern_type": "2",
        "hard_pattern_type": "0",
        "action_num": "1",
        "ready": "FALSE",
        "": ""
    },
    {
        "time": "8.06",
        "simple_pattern_type": "2",
        "hard_pattern_type": "0",
        "action_num": "1",
        "ready": "FALSE",
        "": ""
    },
    {
        "time": "8.25",
        "simple_pattern_type": "2",
        "hard_pattern_type": "0",
        "action_num": "0",
        "ready": "FALSE",
        "": ""
    },
    {
        "time": "9",
        "simple_pattern_type": "2",
        "hard_pattern_type": "0",
        "action_num": "2",
        "ready": "FALSE",
        "": ""
    },
    {
        "time": "9.75",
        "simple_pattern_type": "2",
        "hard_pattern_type": "0",
        "action_num": "2",
        "ready": "FALSE",
        "": ""
    },
    {
        "time": "10.12",
        "simple_pattern_type": "2",
        "hard_pattern_type": "0",
        "action_num": "2",
        "ready": "FALSE",
        "": ""
    },
    {
        "time": "10.315",
        "simple_pattern_type": "2",
        "hard_pattern_type": "0",
        "action_num": "2",
        "ready": "FALSE",
        "": ""
    },
    {
        "time": "10.5",
        "simple_pattern_type": "2",
        "hard_pattern_type": "0",
        "action_num": "2",
        "ready": "FALSE",
        "": ""
    },
    {
        "time": "11.06",
        "simple_pattern_type": "2",
        "hard_pattern_type": "0",
        "action_num": "2",
        "ready": "FALSE",
        "": ""
    },
    {
        "time": "11.25",
        "simple_pattern_type": "2",
        "hard_pattern_type": "0",
        "action_num": "0",
        "ready": "FALSE",
        "": ""
    },
    {
        "time": "12",
        "simple_pattern_type": "2",
        "hard_pattern_type": "0",
        "action_num": "1",
        "ready": "FALSE",
        "": ""
    },
    {
        "time": "12.75",
        "simple_pattern_type": "2",
        "hard_pattern_type": "0",
        "action_num": "1",
        "ready": "FALSE",
        "": ""
    },
    {
        "time": "13.12",
        "simple_pattern_type": "2",
        "hard_pattern_type": "0",
        "action_num": "1",
        "ready": "FALSE",
        "": ""
    },
    {
        "time": "13.315",
        "simple_pattern_type": "2",
        "hard_pattern_type": "0",
        "action_num": "1",
        "ready": "FALSE",
        "": ""
    },
    {
        "time": "13.5",
        "simple_pattern_type": "2",
        "hard_pattern_type": "0",
        "action_num": "1",
        "ready": "FALSE",
        "": ""
    },
    {
        "time": "14.06",
        "simple_pattern_type": "2",
        "hard_pattern_type": "0",
        "action_num": "1",
        "ready": "FALSE",
        "": ""
    },
    {
        "time": "14.25",
        "simple_pattern_type": "2",
        "hard_pattern_type": "0",
        "action_num": "0",
        "ready": "FALSE",
        "": ""
    },
    {
        "time": "15",
        "simple_pattern_type": "2",
        "hard_pattern_type": "0",
        "action_num": "2",
        "ready": "FALSE",
        "": ""
    },
    {
        "time": "15.75",
        "simple_pattern_type": "2",
        "hard_pattern_type": "0",
        "action_num": "2",
        "ready": "FALSE",
        "": ""
    },
    {
        "time": "16.12",
        "simple_pattern_type": "2",
        "hard_pattern_type": "0",
        "action_num": "2",
        "ready": "FALSE",
        "": ""
    },
    {
        "time": "16.315",
        "simple_pattern_type": "2",
        "hard_pattern_type": "0",
        "action_num": "2",
        "ready": "FALSE",
        "": ""
    },
    {
        "time": "16.5",
        "simple_pattern_type": "2",
        "hard_pattern_type": "0",
        "action_num": "2",
        "ready": "FALSE",
        "": ""
    },
    {
        "time": "17.06",
        "simple_pattern_type": "2",
        "hard_pattern_type": "0",
        "action_num": "2",
        "ready": "FALSE",
        "": ""
    },
    {
        "time": "17.25",
        "simple_pattern_type": "3",
        "hard_pattern_type": "0",
        "action_num": "0",
        "ready": "FALSE",
        "": ""
    },
    {
        "time": "18",
        "simple_pattern_type": "3",
        "hard_pattern_type": "0",
        "action_num": "0",
        "ready": "FALSE",
        "": ""
    },
    {
        "time": "25.5",
        "simple_pattern_type": "4",
        "hard_pattern_type": "0",
        "action_num": "0",
        "ready": "FALSE",
        "": ""
    },
    {
        "time": "25.885",
        "simple_pattern_type": "4",
        "hard_pattern_type": "0",
        "action_num": "0",
        "ready": "FALSE",
        "": ""
    },
    {
        "time": "26.25",
        "simple_pattern_type": "4",
        "hard_pattern_type": "0",
        "action_num": "0",
        "ready": "FALSE",
        "": ""
    },
    {
        "time": "27",
        "simple_pattern_type": "4",
        "hard_pattern_type": "0",
        "action_num": "0",
        "ready": "FALSE",
        "": ""
    },
    {
        "time": "27.37",
        "simple_pattern_type": "4",
        "hard_pattern_type": "0",
        "action_num": "0",
        "ready": "FALSE",
        "": ""
    },
    {
        "time": "28.02",
        "simple_pattern_type": "4",
        "hard_pattern_type": "0",
        "action_num": "0",
        "ready": "FALSE",
        "": ""
    },
    {
        "time": "28.5",
        "simple_pattern_type": "4",
        "hard_pattern_type": "0",
        "action_num": "0",
        "ready": "FALSE",
        "": ""
    },
    {
        "time": "28.87",
        "simple_pattern_type": "4",
        "hard_pattern_type": "0",
        "action_num": "0",
        "ready": "FALSE",
        "": ""
    },
    {
        "time": "29.52",
        "simple_pattern_type": "4",
        "hard_pattern_type": "0",
        "action_num": "0",
        "ready": "FALSE",
        "": ""
    },
    {
        "time": "30",
        "simple_pattern_type": "4",
        "hard_pattern_type": "0",
        "action_num": "0",
        "ready": "FALSE",
        "": ""
    },
    {
        "time": "30.37",
        "simple_pattern_type": "4",
        "hard_pattern_type": "0",
        "action_num": "0",
        "ready": "FALSE",
        "": ""
    },
    {
        "time": "31.022",
        "simple_pattern_type": "4",
        "hard_pattern_type": "0",
        "action_num": "0",
        "ready": "FALSE",
        "": ""
    },
    {
        "time": "31.4",
        "simple_pattern_type": "4",
        "hard_pattern_type": "0",
        "action_num": "0",
        "ready": "FALSE",
        "": ""
    },
    {
        "time": "31.88",
        "simple_pattern_type": "4",
        "hard_pattern_type": "0",
        "action_num": "0",
        "ready": "FALSE",
        "": ""
    },
    {
        "time": "32.25",
        "simple_pattern_type": "4",
        "hard_pattern_type": "0",
        "action_num": "0",
        "ready": "FALSE",
        "": ""
    },
    {
        "time": "33",
        "simple_pattern_type": "4",
        "hard_pattern_type": "0",
        "action_num": "0",
        "ready": "FALSE",
        "": ""
    },
    {
        "time": "33.36",
        "simple_pattern_type": "4",
        "hard_pattern_type": "0",
        "action_num": "0",
        "ready": "FALSE",
        "": ""
    },
    {
        "time": "34",
        "simple_pattern_type": "4",
        "hard_pattern_type": "0",
        "action_num": "0",
        "ready": "FALSE",
        "": ""
    },
    {
        "time": "34.5",
        "simple_pattern_type": "4",
        "hard_pattern_type": "0",
        "action_num": "0",
        "ready": "FALSE",
        "": ""
    },
    {
        "time": "34.85",
        "simple_pattern_type": "4",
        "hard_pattern_type": "0",
        "action_num": "0",
        "ready": "FALSE",
        "": ""
    },
    {
        "time": "35.5",
        "simple_pattern_type": "4",
        "hard_pattern_type": "0",
        "action_num": "0",
        "ready": "FALSE",
        "": ""
    },
    {
        "time": "36",
        "simple_pattern_type": "4",
        "hard_pattern_type": "0",
        "action_num": "0",
        "ready": "FALSE",
        "": ""
    },
    {
        "time": "36.3",
        "simple_pattern_type": "4",
        "hard_pattern_type": "0",
        "action_num": "0",
        "ready": "FALSE",
        "": ""
    },
    {
        "time": "37",
        "simple_pattern_type": "4",
        "hard_pattern_type": "0",
        "action_num": "0",
        "ready": "FALSE",
        "": ""
    },
    {
        "time": "37.4",
        "simple_pattern_type": "4",
        "hard_pattern_type": "0",
        "action_num": "0",
        "ready": "FALSE",
        "": ""
    },
    {
        "time": "37.85",
        "simple_pattern_type": "4",
        "hard_pattern_type": "0",
        "action_num": "0",
        "ready": "FALSE",
        "": ""
    },
    {
        "time": "38.25",
        "simple_pattern_type": "4",
        "hard_pattern_type": "0",
        "action_num": "0",
        "ready": "FALSE",
        "": ""
    },
    {
        "time": "38.5",
        "simple_pattern_type": "4",
        "hard_pattern_type": "0",
        "action_num": "0",
        "ready": "FALSE",
        "": ""
    },
    {
        "time": "39.35",
        "simple_pattern_type": "4",
        "hard_pattern_type": "0",
        "action_num": "0",
        "ready": "FALSE",
        "": ""
    },
    {
        "time": "40",
        "simple_pattern_type": "4",
        "hard_pattern_type": "0",
        "action_num": "0",
        "ready": "FALSE",
        "": ""
    },
    {
        "time": "40.85",
        "simple_pattern_type": "4",
        "hard_pattern_type": "0",
        "action_num": "0",
        "ready": "FALSE",
        "": ""
    },
    {
        "time": "41.5",
        "simple_pattern_type": "4",
        "hard_pattern_type": "0",
        "action_num": "0",
        "ready": "FALSE",
        "": ""
    },
    {
        "time": "42.35",
        "simple_pattern_type": "4",
        "hard_pattern_type": "0",
        "action_num": "0",
        "ready": "FALSE",
        "": ""
    },
    {
        "time": "43",
        "simple_pattern_type": "4",
        "hard_pattern_type": "0",
        "action_num": "0",
        "ready": "FALSE",
        "": ""
    },
    {
        "time": "43.5",
        "simple_pattern_type": "4",
        "hard_pattern_type": "0",
        "action_num": "0",
        "ready": "FALSE",
        "": ""
    },
    {
        "time": "44.05",
        "simple_pattern_type": "4",
        "hard_pattern_type": "0",
        "action_num": "0",
        "ready": "FALSE",
        "": ""
    },
    {
        "time": "44.4",
        "simple_pattern_type": "4",
        "hard_pattern_type": "0",
        "action_num": "0",
        "ready": "FALSE",
        "": ""
    },
    {
        "time": "44.8",
        "simple_pattern_type": "4",
        "hard_pattern_type": "0",
        "action_num": "0",
        "ready": "FALSE",
        "": ""
    }
]